reservoirdb/__init__.py
reservoirdb/commands.py
reservoirdb/protocol.py
reservoirdb/py.typed
reservoirdb/session.py
reservoirdb/state.py
reservoirdb-0.1.0.dist-info/WHEEL
reservoirdb-0.1.0.dist-info/METADATA
reservoirdb-0.1.0.dist-info/RECORD
