Metadata-Version: 2.1
Name: reservoirdb
Version: 0.1.0
Summary: 
Author: Ruan Pearce-Authers
Author-email: ruan@reservoirdb.com
Requires-Python: >=3.7.1,<4.0.0
Classifier: Programming Language :: Python :: 3
Classifier: Programming Language :: Python :: 3.8
Classifier: Programming Language :: Python :: 3.9
Requires-Dist: aiohttp (>=3.7.3,<4.0.0)
Requires-Dist: dacite (>=1.6.0,<2.0.0)
Requires-Dist: pandas (>=1.2.2,<2.0.0)
Requires-Dist: pyarrow (>=3.0.0,<4.0.0)
Requires-Dist: typing-extensions (>=3.7.4,<4.0.0)
